{
  "mlir.rvv_vp_intrinsic_add": 316,
  "mlir.rvv_vp_intrinsic_add_scalable": 502,
  "mlir.hello": 78,
  "mlir.stripmining": 8914,
  "asm.mmm": 58605,
  "asm.smoke": 4456,
  "intrinsic.conv2d_less_m2": 51188,
  "codegen.vaadd_vv": 176252,
  "codegen.vaadd_vx": 441466,
  "codegen.vaaddu_vv": 176252,
  "codegen.vaaddu_vx": 441466,
  "codegen.vadc_vim": 41190,
  "codegen.vadc_vvm": 21544,
  "codegen.vadc_vxm": 54656,
  "codegen.vadd_vi": 79817,
  "codegen.vadd_vv": 44056,
  "codegen.vadd_vx": 110376,
  "codegen.vand_vi": 79808,
  "codegen.vand_vv": 44056,
  "codegen.vand_vx": 110381,
  "codegen.vasub_vv": 176252,
  "codegen.vasub_vx": 441466,
  "codegen.vasubu_vv": 176252,
  "codegen.vasubu_vx": 441466,
  "codegen.vcompress_vm": 55668,
  "codegen.vcpop_m": 1938,
  "codegen.vdiv_vv": 56350,
  "codegen.vdiv_vx": 313650,
  "codegen.vdivu_vv": 56510,
  "codegen.vdivu_vx": 330689,
  "codegen.vfirst_m": 1698,
  "codegen.vid_v": 18300,
  "codegen.viota_m": 114919,
  "codegen.vl1re16_v": 863,
  "codegen.vl1re32_v": 863,
  "codegen.vl1re8_v": 863,
  "codegen.vl2re16_v": 1515,
  "codegen.vl2re32_v": 1515,
  "codegen.vl2re8_v": 1515,
  "codegen.vl4re16_v": 2835,
  "codegen.vl4re32_v": 2835,
  "codegen.vl4re8_v": 2835,
  "codegen.vl8re16_v": 5451,
  "codegen.vl8re32_v": 5451,
  "codegen.vl8re8_v": 5451,
  "codegen.vle16_v": 7932,
  "codegen.vle16ff_v": 23735,
  "codegen.vle32_v": 6457,
  "codegen.vle32ff_v": 13825,
  "codegen.vle8_v": 9166,
  "codegen.vle8ff_v": 43714,
  "codegen.vlm_v": 463,
  "codegen.vloxei16_v": 67989,
  "codegen.vloxei32_v": 36269,
  "codegen.vloxei8_v": 105409,
  "codegen.vloxseg2ei16_v": 71372,
  "codegen.vloxseg2ei32_v": 38475,
  "codegen.vloxseg2ei8_v": 91866,
  "codegen.vloxseg3ei16_v": 49773,
  "codegen.vloxseg3ei32_v": 30012,
  "codegen.vloxseg3ei8_v": 69103,
  "codegen.vloxseg4ei16_v": 60452,
  "codegen.vloxseg4ei32_v": 35164,
  "codegen.vloxseg4ei8_v": 85723,
  "codegen.vloxseg5ei16_v": 36150,
  "codegen.vloxseg5ei32_v": 15855,
  "codegen.vloxseg5ei8_v": 49452,
  "codegen.vloxseg6ei16_v": 41125,
  "codegen.vloxseg6ei32_v": 17567,
  "codegen.vloxseg6ei8_v": 56800,
  "codegen.vloxseg7ei16_v": 46100,
  "codegen.vloxseg7ei32_v": 19279,
  "codegen.vloxseg7ei8_v": 64148,
  "codegen.vloxseg8ei16_v": 51075,
  "codegen.vloxseg8ei32_v": 20991,
  "codegen.vloxseg8ei8_v": 71496,
  "codegen.vlse16_v": 109531,
  "codegen.vlse32_v": 63071,
  "codegen.vlse8_v": 207513,
  "codegen.vlseg2e16_v": 6862,
  "codegen.vlseg2e32_v": 5419,
  "codegen.vlseg2e8_v": 8027,
  "codegen.vlseg3e16_v": 5185,
  "codegen.vlseg3e32_v": 3927,
  "codegen.vlseg3e8_v": 6702,
  "codegen.vlseg4e16_v": 5401,
  "codegen.vlseg4e32_v": 4116,
  "codegen.vlseg4e8_v": 6962,
  "codegen.vlseg5e16_v": 4003,
  "codegen.vlseg5e32_v": 2229,
  "codegen.vlseg5e8_v": 5262,
  "codegen.vlseg6e16_v": 4115,
  "codegen.vlseg6e32_v": 2295,
  "codegen.vlseg6e8_v": 5402,
  "codegen.vlseg7e16_v": 4227,
  "codegen.vlseg7e32_v": 2361,
  "codegen.vlseg7e8_v": 5536,
  "codegen.vlseg8e16_v": 4339,
  "codegen.vlseg8e32_v": 2427,
  "codegen.vlseg8e8_v": 5676,
  "codegen.vlsseg2e16_v": 106237,
  "codegen.vlsseg2e32_v": 54213,
  "codegen.vlsseg2e8_v": 195105,
  "codegen.vlsseg3e16_v": 76298,
  "codegen.vlsseg3e32_v": 37228,
  "codegen.vlsseg3e8_v": 154279,
  "codegen.vlsseg4e16_v": 96403,
  "codegen.vlsseg4e32_v": 45808,
  "codegen.vlsseg4e8_v": 198944,
  "codegen.vlsseg5e16_v": 59140,
  "codegen.vlsseg5e32_v": 20722,
  "codegen.vlsseg5e8_v": 124828,
  "codegen.vlsseg6e16_v": 68710,
  "codegen.vlsseg6e32_v": 23572,
  "codegen.vlsseg6e8_v": 146578,
  "codegen.vlsseg7e16_v": 78280,
  "codegen.vlsseg7e32_v": 26422,
  "codegen.vlsseg7e8_v": 168328,
  "codegen.vlsseg8e16_v": 87850,
  "codegen.vlsseg8e32_v": 29272,
  "codegen.vlsseg8e8_v": 190078,
  "codegen.vluxei16_v": 67989,
  "codegen.vluxei32_v": 36269,
  "codegen.vluxei8_v": 105409,
  "codegen.vluxseg2ei16_v": 71372,
  "codegen.vluxseg2ei32_v": 38475,
  "codegen.vluxseg2ei8_v": 91866,
  "codegen.vluxseg3ei16_v": 49773,
  "codegen.vluxseg3ei32_v": 30012,
  "codegen.vluxseg3ei8_v": 69103,
  "codegen.vluxseg4ei16_v": 60452,
  "codegen.vluxseg4ei32_v": 35164,
  "codegen.vluxseg4ei8_v": 85723,
  "codegen.vluxseg5ei16_v": 36150,
  "codegen.vluxseg5ei32_v": 15855,
  "codegen.vluxseg5ei8_v": 49452,
  "codegen.vluxseg6ei16_v": 41125,
  "codegen.vluxseg6ei32_v": 17567,
  "codegen.vluxseg6ei8_v": 56800,
  "codegen.vluxseg7ei16_v": 46100,
  "codegen.vluxseg7ei32_v": 19279,
  "codegen.vluxseg7ei8_v": 64148,
  "codegen.vluxseg8ei16_v": 51075,
  "codegen.vluxseg8ei32_v": 20991,
  "codegen.vluxseg8ei8_v": 71496,
  "codegen.vmacc_vv": 52930,
  "codegen.vmacc_vx": 125060,
  "codegen.vmadc_vi": 41403,
  "codegen.vmadc_vim": 45961,
  "codegen.vmadc_vv": 14308,
  "codegen.vmadc_vvm": 20614,
  "codegen.vmadc_vx": 56799,
  "codegen.vmadc_vxm": 61351,
  "codegen.vmadd_vv": 52930,
  "codegen.vmadd_vx": 125060,
  "codegen.vmand_mm": 13677,
  "codegen.vmandn_mm": 13677,
  "codegen.vmax_vv": 44056,
  "codegen.vmax_vx": 110376,
  "codegen.vmaxu_vv": 44056,
  "codegen.vmaxu_vx": 110376,
  "codegen.vmerge_vim": 45507,
  "codegen.vmerge_vvm": 22357,
  "codegen.vmerge_vxm": 60696,
  "codegen.vmin_vv": 44056,
  "codegen.vmin_vx": 110376,
  "codegen.vminu_vv": 44056,
  "codegen.vminu_vx": 110376,
  "codegen.vmnand_mm": 13677,
  "codegen.vmnor_mm": 13677,
  "codegen.vmor_mm": 13677,
  "codegen.vmorn_mm": 13677,
  "codegen.vmsbc_vv": 14308,
  "codegen.vmsbc_vvm": 20614,
  "codegen.vmsbc_vx": 56799,
  "codegen.vmsbc_vxm": 61351,
  "codegen.vmsbf_m": 1649,
  "codegen.vmseq_vi": 105615,
  "codegen.vmseq_vv": 43501,
  "codegen.vmseq_vx": 144104,
  "codegen.vmsgt_vi": 105615,
  "codegen.vmsgt_vv": 43501,
  "codegen.vmsgt_vx": 144104,
  "codegen.vmsgtu_vi": 105615,
  "codegen.vmsgtu_vv": 43501,
  "codegen.vmsgtu_vx": 144104,
  "codegen.vmsif_m": 1649,
  "codegen.vmsle_vi": 105615,
  "codegen.vmsle_vv": 43501,
  "codegen.vmsle_vx": 144104,
  "codegen.vmsleu_vi": 105615,
  "codegen.vmsleu_vv": 43501,
  "codegen.vmsleu_vx": 144104,
  "codegen.vmslt_vv": 43501,
  "codegen.vmslt_vx": 144104,
  "codegen.vmsltu_vv": 43501,
  "codegen.vmsltu_vx": 144104,
  "codegen.vmsne_vi": 105615,
  "codegen.vmsne_vv": 43501,
  "codegen.vmsne_vx": 144104,
  "codegen.vmsof_m": 1649,
  "codegen.vmul_vv": 44056,
  "codegen.vmul_vx": 146690,
  "codegen.vmulh_vv": 44056,
  "codegen.vmulh_vx": 146690,
  "codegen.vmulhsu_vv": 44056,
  "codegen.vmulhsu_vx": 146690,
  "codegen.vmulhu_vv": 44056,
  "codegen.vmulhu_vx": 146690,
  "codegen.vmv_s_x": 1049,
  "codegen.vmv_v_i": 21628,
  "codegen.vmv_v_v": 10558,
  "codegen.vmv_v_x": 6745,
  "codegen.vmv_x_s": 1727,
  "codegen.vmv1r_v": 1353,
  "codegen.vmv2r_v": 1543,
  "codegen.vmv4r_v": 2477,
  "codegen.vmv8r_v": 3357,
  "codegen.vmxnor_mm": 13677,
  "codegen.vmxor_mm": 13677,
  "codegen.vnclip_wi": 208242,
  "codegen.vnclip_wv": 101743,
  "codegen.vnclip_wx": 284175,
  "codegen.vnclipu_wi": 208242,
  "codegen.vnclipu_wv": 101743,
  "codegen.vnclipu_wx": 284175,
  "codegen.vnmsac_vv": 52930,
  "codegen.vnmsac_vx": 125060,
  "codegen.vnmsub_vv": 52930,
  "codegen.vnmsub_vx": 125060,
  "codegen.vnsra_wi": 51992,
  "codegen.vnsra_wv": 25435,
  "codegen.vnsra_wx": 70678,
  "codegen.vnsrl_wi": 51992,
  "codegen.vnsrl_wv": 25435,
  "codegen.vnsrl_wx": 70678,
  "codegen.vor_vi": 79808,
  "codegen.vor_vv": 44056,
  "codegen.vor_vx": 110381,
  "codegen.vredand_vs": 41802,
  "codegen.vredmax_vs": 41802,
  "codegen.vredmaxu_vs": 41802,
  "codegen.vredmin_vs": 41802,
  "codegen.vredminu_vs": 41802,
  "codegen.vredor_vs": 41802,
  "codegen.vredsum_vs": 41802,
  "codegen.vredxor_vs": 41802,
  "codegen.vrem_vv": 56350,
  "codegen.vrem_vx": 313650,
  "codegen.vremu_vv": 56510,
  "codegen.vremu_vx": 330689,
  "codegen.vrgather_vi": 96032,
  "codegen.vrgather_vv": 272138,
  "codegen.vrgather_vx": 127966,
  "codegen.vrgatherei16_vv": 198694,
  "codegen.vrsub_vi": 79817,
  "codegen.vrsub_vx": 110376,
  "codegen.vs1r_v": 1038,
  "codegen.vs2r_v": 1722,
  "codegen.vs4r_v": 3090,
  "codegen.vs8r_v": 5826,
  "codegen.vsadd_vi": 79817,
  "codegen.vsadd_vv": 44056,
  "codegen.vsadd_vx": 107419,
  "codegen.vsaddu_vi": 79817,
  "codegen.vsaddu_vv": 44056,
  "codegen.vsaddu_vx": 107419,
  "codegen.vsbc_vvm": 21544,
  "codegen.vsbc_vxm": 81590,
  "codegen.vse16_v": 9225,
  "codegen.vse32_v": 7690,
  "codegen.vse8_v": 10739,
  "codegen.vsetivli": 0,
  "codegen.vsetvl": 0,
  "codegen.vsetvli": 0,
  "codegen.vsext_vf2": 60410,
  "codegen.vsext_vf4": 9779,
  "codegen.vslide1down_vx": 2458557,
  "codegen.vslide1up_vx": 2454717,
  "codegen.vslidedown_vi": 1723299,
  "codegen.vslidedown_vx": 2456189,
  "codegen.vslideup_vi": 1720987,
  "codegen.vslideup_vx": 2454785,
  "codegen.vsll_vi": 85765,
  "codegen.vsll_vv": 45173,
  "codegen.vsll_vx": 118711,
  "codegen.vsm_v": 630,
  "codegen.vsmul_vv": 176252,
  "codegen.vsmul_vx": 441486,
  "codegen.vsoxei16_v": 72818,
  "codegen.vsoxei32_v": 39701,
  "codegen.vsoxei8_v": 110912,
  "codegen.vsoxseg2ei16_v": 76512,
  "codegen.vsoxseg2ei32_v": 42034,
  "codegen.vsoxseg2ei8_v": 96775,
  "codegen.vsoxseg3ei16_v": 53721,
  "codegen.vsoxseg3ei32_v": 33528,
  "codegen.vsoxseg3ei8_v": 73205,
  "codegen.vsoxseg4ei16_v": 64400,
  "codegen.vsoxseg4ei32_v": 38680,
  "codegen.vsoxseg4ei8_v": 89825,
  "codegen.vsoxseg5ei16_v": 38921,
  "codegen.vsoxseg5ei32_v": 17941,
  "codegen.vsoxseg5ei8_v": 52665,
  "codegen.vsoxseg6ei16_v": 43896,
  "codegen.vsoxseg6ei32_v": 19653,
  "codegen.vsoxseg6ei8_v": 60013,
  "codegen.vsoxseg7ei16_v": 48871,
  "codegen.vsoxseg7ei32_v": 21365,
  "codegen.vsoxseg7ei8_v": 67361,
  "codegen.vsoxseg8ei16_v": 53846,
  "codegen.vsoxseg8ei32_v": 23077,
  "codegen.vsoxseg8ei8_v": 74709,
  "codegen.vsra_vi": 85765,
  "codegen.vsra_vv": 45173,
  "codegen.vsra_vx": 118711,
  "codegen.vsrl_vi": 85765,
  "codegen.vsrl_vv": 45173,
  "codegen.vsrl_vx": 118711,
  "codegen.vsse16_v": 131025,
  "codegen.vsse32_v": 87507,
  "codegen.vsse8_v": 215687,
  "codegen.vsseg2e16_v": 8091,
  "codegen.vsseg2e32_v": 6553,
  "codegen.vsseg2e8_v": 9657,
  "codegen.vsseg3e16_v": 6457,
  "codegen.vsseg3e32_v": 4711,
  "codegen.vsseg3e8_v": 7973,
  "codegen.vsseg4e16_v": 6849,
  "codegen.vsseg4e32_v": 5079,
  "codegen.vsseg4e8_v": 8387,
  "codegen.vsseg5e16_v": 4791,
  "codegen.vsseg5e32_v": 2631,
  "codegen.vsseg5e8_v": 6525,
  "codegen.vsseg6e16_v": 4951,
  "codegen.vsseg6e32_v": 2761,
  "codegen.vsseg6e8_v": 6697,
  "codegen.vsseg7e16_v": 5111,
  "codegen.vsseg7e32_v": 2891,
  "codegen.vsseg7e8_v": 6869,
  "codegen.vsseg8e16_v": 5271,
  "codegen.vsseg8e32_v": 3021,
  "codegen.vsseg8e8_v": 7041,
  "codegen.vssra_vi": 343082,
  "codegen.vssra_vv": 180719,
  "codegen.vssra_vx": 697181,
  "codegen.vssrl_vi": 343082,
  "codegen.vssrl_vv": 180719,
  "codegen.vssrl_vx": 697181,
  "codegen.vssseg2e16_v": 122715,
  "codegen.vssseg2e32_v": 74133,
  "codegen.vssseg2e8_v": 199473,
  "codegen.vssseg3e16_v": 91801,
  "codegen.vssseg3e32_v": 53199,
  "codegen.vssseg3e8_v": 161143,
  "codegen.vssseg4e16_v": 107885,
  "codegen.vssseg4e32_v": 60063,
  "codegen.vssseg4e8_v": 196875,
  "codegen.vssseg5e16_v": 70887,
  "codegen.vssseg5e32_v": 30505,
  "codegen.vssseg5e8_v": 130613,
  "codegen.vssseg6e16_v": 78543,
  "codegen.vssseg6e32_v": 32785,
  "codegen.vssseg6e8_v": 148013,
  "codegen.vssseg7e16_v": 86199,
  "codegen.vssseg7e32_v": 35065,
  "codegen.vssseg7e8_v": 165413,
  "codegen.vssseg8e16_v": 93855,
  "codegen.vssseg8e32_v": 37345,
  "codegen.vssseg8e8_v": 182813,
  "codegen.vssub_vv": 44056,
  "codegen.vssub_vx": 164817,
  "codegen.vssubu_vv": 44056,
  "codegen.vssubu_vx": 164817,
  "codegen.vsub_vv": 44056,
  "codegen.vsub_vx": 164817,
  "codegen.vsuxei16_v": 72818,
  "codegen.vsuxei32_v": 39701,
  "codegen.vsuxei8_v": 110912,
  "codegen.vsuxseg2ei16_v": 76512,
  "codegen.vsuxseg2ei32_v": 42034,
  "codegen.vsuxseg2ei8_v": 96775,
  "codegen.vsuxseg3ei16_v": 53721,
  "codegen.vsuxseg3ei32_v": 33528,
  "codegen.vsuxseg3ei8_v": 73205,
  "codegen.vsuxseg4ei16_v": 64400,
  "codegen.vsuxseg4ei32_v": 38680,
  "codegen.vsuxseg4ei8_v": 89825,
  "codegen.vsuxseg5ei16_v": 38921,
  "codegen.vsuxseg5ei32_v": 17941,
  "codegen.vsuxseg5ei8_v": 52665,
  "codegen.vsuxseg6ei16_v": 43896,
  "codegen.vsuxseg6ei32_v": 19653,
  "codegen.vsuxseg6ei8_v": 60013,
  "codegen.vsuxseg7ei16_v": 48871,
  "codegen.vsuxseg7ei32_v": 21365,
  "codegen.vsuxseg7ei8_v": 67361,
  "codegen.vsuxseg8ei16_v": 53846,
  "codegen.vsuxseg8ei32_v": 23077,
  "codegen.vsuxseg8ei8_v": 74709,
  "codegen.vwadd_vv": 25321,
  "codegen.vwadd_vx": 66546,
  "codegen.vwadd_wv": 27317,
  "codegen.vwadd_wx": 76571,
  "codegen.vwaddu_vv": 25321,
  "codegen.vwaddu_vx": 66546,
  "codegen.vwaddu_wv": 27317,
  "codegen.vwaddu_wx": 76571,
  "codegen.vwmacc_vv": 31512,
  "codegen.vwmacc_vx": 75262,
  "codegen.vwmaccsu_vv": 31512,
  "codegen.vwmaccsu_vx": 75262,
  "codegen.vwmaccu_vv": 31512,
  "codegen.vwmaccu_vx": 75262,
  "codegen.vwmaccus_vx": 75262,
  "codegen.vwmul_vv": 25321,
  "codegen.vwmul_vx": 88698,
  "codegen.vwmulsu_vv": 25321,
  "codegen.vwmulsu_vx": 88698,
  "codegen.vwmulu_vv": 25321,
  "codegen.vwmulu_vx": 88698,
  "codegen.vwredsum_vs": 23855,
  "codegen.vwredsumu_vs": 23855,
  "codegen.vwsub_vv": 25321,
  "codegen.vwsub_vx": 66546,
  "codegen.vwsub_wv": 27317,
  "codegen.vwsub_wx": 76571,
  "codegen.vwsubu_vv": 25321,
  "codegen.vwsubu_vx": 66546,
  "codegen.vwsubu_wv": 27317,
  "codegen.vwsubu_wx": 76571,
  "codegen.vxor_vi": 79808,
  "codegen.vxor_vv": 44056,
  "codegen.vxor_vx": 110381,
  "codegen.vzext_vf2": 60410,
  "codegen.vzext_vf4": 9779
}